SyncCounter.vhd
-- UFMG
-- 05/12/2023
-- Ricardo de Oliveira Duarte
-- A 4-bit synchronous counter, with synchronous reset, synchronous parallel load, load signal control, and start_count signal control.

library ieee;
use ieee.std_logic_1164.ALL;
use ieee.numeric_std.all;

entity SyncCounter is
    Port ( clk : in STD_LOGIC;
           rst : in STD_LOGIC;
           load : in STD_LOGIC;
           start_count : in STD_LOGIC;
           parallel_data : in STD_LOGIC_VECTOR(3 downto 0);
           count : out STD_LOGIC_VECTOR(3 downto 0));
end SyncCounter;

architecture Behavioral of SyncCounter is
    signal counter_reg : STD_LOGIC_VECTOR(3 downto 0) := "0000";
begin
    process(clk, rst)
    begin
        if rst = '1' then
            counter_reg <= "0000";
        elsif rising_edge(clk) then
            if (start_count = '0' and load = '1') then
                counter_reg <= parallel_data;
            elsif (start_count = '1' and load = '0') then
                counter_reg <= std_logic_vector(unsigned(counter_reg) + 1);
			else 
				counter_reg <= counter_reg;
            end if;
        end if;
    end process;

    count <= counter_reg;
end Behavioral;

Testbench_SyncCounter.vhd
-- UFMG
-- 05/12/2023
-- Ricardo de Oliveira Duarte
-- A Testbench_SyncCounter to a 4-bit synchronous counter, with synchronous reset, synchronous parallel load, load signal control
-- and start_count signal control.

library ieee;
use ieee.std_logic_1164.ALL;
use ieee.numeric_std.all;

entity Testbench_SyncCounter is
end Testbench_SyncCounter;

architecture Behavioral of Testbench_SyncCounter is
    signal clk_tb, rst_tb, load_tb, start_count_tb : STD_LOGIC := '0';
    signal parallel_data_tb : STD_LOGIC_VECTOR(3 downto 0) := "0000";
    signal count_tb : STD_LOGIC_VECTOR(3 downto 0);

    constant clk_period : time := 10 ns;  -- Define the clock period

    component SyncCounter
        Port ( clk : in STD_LOGIC;
               rst : in STD_LOGIC;
               load : in STD_LOGIC;
               start_count : in STD_LOGIC;
               parallel_data : in STD_LOGIC_VECTOR(3 downto 0);
               count : out STD_LOGIC_VECTOR(3 downto 0));
    end component;

begin
    uut: SyncCounter
        port map (clk => clk_tb,
                  rst => rst_tb,
                  load => load_tb,
                  start_count => start_count_tb,
                  parallel_data => parallel_data_tb,
                  count => count_tb);

    -- Clock generation process
    process
    begin
        while now < 1000 ns loop
            clk_tb <= '0';
            wait for clk_period / 2;
            clk_tb <= '1';
            wait for clk_period / 2;
        end loop;
        wait;
    end process;

    -- Stimulus process
    process
    begin
        rst_tb <= '1';  -- Reset initially
        wait for 20 ns;

        rst_tb <= '0';  -- De-assert reset
        wait for 20 ns;

        load_tb <= '1';  -- Load initial data
        parallel_data_tb <= "1010";
        wait for 20 ns;

        load_tb <= '0';  -- Start counting
        wait for 20 ns;

        start_count_tb <= '1';  -- Enable counting
        wait for 200 ns;

        start_count_tb <= '0';  -- Stop counting
        wait for 20 ns;

        wait;
    end process;

end Behavioral;

Testbench_SyncCounter.vcd
$date
  Tue Dec 05 09:22:31 2023
$end
$version
  GHDL v0
$end
$timescale
  1 ns
$end
$scope module standard $end
$upscope $end
$scope module std_logic_1164 $end
$upscope $end
$scope module numeric_std $end
$upscope $end
$scope module testbench_synccounter $end
$var reg 1 ! clk_tb $end
$var reg 1 " rst_tb $end
$var reg 1 # load_tb $end
$var reg 1 $ start_count_tb $end
$var reg 4 % parallel_data_tb[3:0] $end
$var reg 4 & count_tb[3:0] $end
$scope module uut $end
$var reg 1 ' clk $end
$var reg 1 ( rst $end
$var reg 1 ) load $end
$var reg 1 * start_count $end
$var reg 4 + parallel_data[3:0] $end
$var reg 4 , count[3:0] $end
$var reg 4 - counter_reg[3:0] $end
$upscope $end
$upscope $end
$enddefinitions $end
#0
0!
1"
0#
0$
b0000 %
b0000 &
0'
1(
0)
0*
b0000 +
b0000 ,
b0000 -
#5000000
1!
1'
#10000000
0!
0'
#15000000
1!
1'
#20000000
0!
0"
0'
0(
#25000000
1!
1'
#30000000
0!
0'
#35000000
1!
1'
#40000000
0!
1#
b1010 %
0'
1)
b1010 +
#45000000
1!
b1010 &
1'
b1010 ,
b1010 -
#50000000
0!
0'
#55000000
1!
1'
#60000000
0!
0#
0'
0)
#65000000
1!
1'
#70000000
0!
0'
#75000000
1!
1'
#80000000
0!
1$
0'
1*
#85000000
1!
b1011 &
1'
b1011 ,
b1011 -
#90000000
0!
0'
#95000000
1!
b1100 &
1'
b1100 ,
b1100 -
#100000000
0!
0'
#105000000
1!
b1101 &
1'
b1101 ,
b1101 -
#110000000
0!
0'
#115000000
1!
b1110 &
1'
b1110 ,
b1110 -
#120000000
0!
0'
#125000000
1!
b1111 &
1'
b1111 ,
b1111 -
#130000000
0!
0'
#135000000
1!
b0000 &
1'
b0000 ,
b0000 -
#140000000
0!
0'
#145000000
1!
b0001 &
1'
b0001 ,
b0001 -
#150000000
0!
0'
#155000000
1!
b0010 &
1'
b0010 ,
b0010 -
#160000000
0!
0'
#165000000
1!
b0011 &
1'
b0011 ,
b0011 -
#170000000
0!
0'
#175000000
1!
b0100 &
1'
b0100 ,
b0100 -
#180000000
0!
0'
#185000000
1!
b0101 &
1'
b0101 ,
b0101 -
#190000000
0!
0'
#195000000
1!
b0110 &
1'
b0110 ,
b0110 -
#200000000
0!
0'
#205000000
1!
b0111 &
1'
b0111 ,
b0111 -
#210000000
0!
0'
#215000000
1!
b1000 &
1'
b1000 ,
b1000 -
#220000000
0!
0'
#225000000
1!
b1001 &
1'
b1001 ,
b1001 -
#230000000
0!
0'
#235000000
1!
b1010 &
1'
b1010 ,
b1010 -
#240000000
0!
0'
#245000000
1!
b1011 &
1'
b1011 ,
b1011 -
#250000000
0!
0'
#255000000
1!
b1100 &
1'
b1100 ,
b1100 -
#260000000
0!
0'
#265000000
1!
b1101 &
1'
b1101 ,
b1101 -
#270000000
0!
0'
#275000000
1!
b1110 &
1'
b1110 ,
b1110 -
#280000000
0!
0$
0'
0*
